mailfmt.py
mailfmt-1.0.3.dist-info/METADATA
mailfmt-1.0.3.dist-info/WHEEL
mailfmt-1.0.3.dist-info/entry_points.txt
mailfmt-1.0.3.dist-info/licenses/LICENSE
mailfmt-1.0.3.dist-info/RECORD
