Metadata-Version: 2.4
Name: mailfmt
Version: 1.0.3
Summary: Heuristic plain text email formatter.
Project-URL: Repository, https://git.ficd.sh/ficd/mailfmt
Author-email: Daniel Fichtinger <daniel@ficd.ca>
License-Expression: ISC
License-File: LICENSE
Keywords: cli,email,formatter
Requires-Python: >=3.11
